[
  {
    "question": "New Rihanna Album before GTA VI?",
    "yes": 50,
    "volume": 10704,
    "category": "\ud83c\udfac"
  },
  {
    "question": "New Playboi Carti Album before GTA VI?",
    "yes": 50,
    "volume": 46,
    "category": "\ud83c\udfac"
  },
  {
    "question": "Will Jesus Christ return before GTA VI?",
    "yes": 50,
    "volume": 1174,
    "category": "\ud83c\udfac"
  },
  {
    "question": "Trump out as President before GTA VI?",
    "yes": 50,
    "volume": 261,
    "category": "\ud83c\udfdb\ufe0f"
  },
  {
    "question": "Will China invades Taiwan before GTA VI?",
    "yes": 50,
    "volume": 5208,
    "category": "\ud83c\udfac"
  },
  {
    "question": "Will bitcoin hit $1m before GTA VI?",
    "yes": 50,
    "volume": 547,
    "category": "\ud83d\udc8e"
  },
  {
    "question": "Will Harvey Weinstein be sentenced to no prison time?",
    "yes": 50,
    "volume": 234,
    "category": "\u2753"
  },
  {
    "question": "Will Harvey Weinstein be sentenced to less than 5 years in prison?",
    "yes": 50,
    "volume": 68,
    "category": "\u2753"
  },
  {
    "question": "Will Harvey Weinstein be sentenced to between 5 and 10 years in prison?",
    "yes": 50,
    "volume": 62,
    "category": "\u2753"
  },
  {
    "question": "Will Harvey Weinstein be sentenced to between 10 and 20 years in prison?",
    "yes": 50,
    "volume": 61,
    "category": "\u2753"
  },
  {
    "question": "Will Harvey Weinstein be sentenced to between 20 and 30 years in prison?",
    "yes": 50,
    "volume": 335,
    "category": "\u2753"
  },
  {
    "question": "Will Harvey Weinstein be sentenced to more than 30 years in prison?",
    "yes": 50,
    "volume": 23,
    "category": "\u2753"
  },
  {
    "question": "Will the Carolina Hurricanes win the 2026 NHL Stanley Cup?",
    "yes": 50,
    "volume": 66113,
    "category": "\u2753"
  },
  {
    "question": "Will the Vegas Golden Knights win the 2026 NHL Stanley Cup?",
    "yes": 50,
    "volume": 89237,
    "category": "\u2753"
  },
  {
    "question": "Will the New York Knicks win the 2026 NBA Finals?",
    "yes": 50,
    "volume": 851974,
    "category": "\u26bd"
  },
  {
    "question": "Will the San Antonio Spurs win the 2026 NBA Finals?",
    "yes": 50,
    "volume": 755159,
    "category": "\u26bd"
  },
  {
    "question": "Will MegaETH perform an airdrop by June 30? ",
    "yes": 50,
    "volume": 442,
    "category": "\ud83d\udc8e"
  },
  {
    "question": "Will Spain win the 2026 FIFA World Cup?",
    "yes": 50,
    "volume": 920041,
    "category": "\u26bd"
  },
  {
    "question": "Will England win the 2026 FIFA World Cup?",
    "yes": 50,
    "volume": 777757,
    "category": "\u26bd"
  },
  {
    "question": "Will France win the 2026 FIFA World Cup?",
    "yes": 50,
    "volume": 719809,
    "category": "\u26bd"
  },
  {
    "question": "Will Brazil win the 2026 FIFA World Cup?",
    "yes": 50,
    "volume": 352651,
    "category": "\u26bd"
  },
  {
    "question": "Will Argentina win the 2026 FIFA World Cup?",
    "yes": 50,
    "volume": 334113,
    "category": "\u26bd"
  },
  {
    "question": "Will Germany win the 2026 FIFA World Cup?",
    "yes": 50,
    "volume": 1129119,
    "category": "\u26bd"
  },
  {
    "question": "Will Portugal win the 2026 FIFA World Cup?",
    "yes": 50,
    "volume": 737711,
    "category": "\u26bd"
  },
  {
    "question": "Will Netherlands win the 2026 FIFA World Cup?",
    "yes": 50,
    "volume": 783460,
    "category": "\ud83d\udc8e"
  },
  {
    "question": "Will USA win the 2026 FIFA World Cup?",
    "yes": 50,
    "volume": 1550912,
    "category": "\u26bd"
  },
  {
    "question": "Will Uruguay win the 2026 FIFA World Cup?",
    "yes": 50,
    "volume": 708813,
    "category": "\u26bd"
  },
  {
    "question": "Will Mexico win the 2026 FIFA World Cup?",
    "yes": 50,
    "volume": 1682994,
    "category": "\u26bd"
  },
  {
    "question": "Will Belgium win the 2026 FIFA World Cup?",
    "yes": 50,
    "volume": 1375671,
    "category": "\u26bd"
  },
  {
    "question": "Will Colombia win the 2026 FIFA World Cup?",
    "yes": 50,
    "volume": 717963,
    "category": "\u26bd"
  },
  {
    "question": "Will Japan win the 2026 FIFA World Cup?",
    "yes": 50,
    "volume": 743435,
    "category": "\u26bd"
  },
  {
    "question": "Will Norway win the 2026 FIFA World Cup?",
    "yes": 50,
    "volume": 993091,
    "category": "\u26bd"
  },
  {
    "question": "Will Canada win the 2026 FIFA World Cup?",
    "yes": 50,
    "volume": 1095718,
    "category": "\u26bd"
  },
  {
    "question": "Will Tunisia win the 2026 FIFA World Cup?",
    "yes": 50,
    "volume": 580707,
    "category": "\u26bd"
  },
  {
    "question": "Will Ecuador win the 2026 FIFA World Cup?",
    "yes": 50,
    "volume": 946358,
    "category": "\u26bd"
  },
  {
    "question": "Will Paraguay win the 2026 FIFA World Cup?",
    "yes": 50,
    "volume": 414190,
    "category": "\u26bd"
  },
  {
    "question": "Will New Zealand win the 2026 FIFA World Cup?",
    "yes": 50,
    "volume": 18000,
    "category": "\u26bd"
  },
  {
    "question": "Will Australia win the 2026 FIFA World Cup?",
    "yes": 50,
    "volume": 480285,
    "category": "\u26bd"
  },
  {
    "question": "Will Iran win the 2026 FIFA World Cup?",
    "yes": 50,
    "volume": 2123409,
    "category": "\u26bd"
  },
  {
    "question": "Will Uzbekistan win the 2026 FIFA World Cup?",
    "yes": 50,
    "volume": 69181,
    "category": "\u26bd"
  },
  {
    "question": "Will South Korea win the 2026 FIFA World Cup?",
    "yes": 50,
    "volume": 1454339,
    "category": "\u26bd"
  },
  {
    "question": "Will Jordan win the 2026 FIFA World Cup?",
    "yes": 50,
    "volume": 9093,
    "category": "\u26bd"
  },
  {
    "question": "Will Morocco win the 2026 FIFA World Cup?",
    "yes": 50,
    "volume": 1506736,
    "category": "\u26bd"
  },
  {
    "question": "Will South Africa win the 2026 FIFA World Cup?",
    "yes": 50,
    "volume": 409742,
    "category": "\u26bd"
  },
  {
    "question": "Will Senegal win the 2026 FIFA World Cup?",
    "yes": 50,
    "volume": 879776,
    "category": "\u26bd"
  },
  {
    "question": "Will Ivory Coast win the 2026 FIFA World Cup?",
    "yes": 50,
    "volume": 738470,
    "category": "\u26bd"
  },
  {
    "question": "Will Ghana win the 2026 FIFA World Cup?",
    "yes": 50,
    "volume": 1061121,
    "category": "\u26bd"
  },
  {
    "question": "Will Egypt win the 2026 FIFA World Cup?",
    "yes": 50,
    "volume": 669478,
    "category": "\u26bd"
  },
  {
    "question": "Will Algeria win the 2026 FIFA World Cup?",
    "yes": 50,
    "volume": 840623,
    "category": "\u26bd"
  },
  {
    "question": "Will Cape Verde win the 2026 FIFA World Cup?",
    "yes": 50,
    "volume": 319290,
    "category": "\u26bd"
  }
]